calculator_val.py
calculator_val-1.0.dist-info/LICENSE
calculator_val-1.0.dist-info/WHEEL
calculator_val-1.0.dist-info/METADATA
calculator_val-1.0.dist-info/RECORD
