Metadata-Version: 2.1
Name: calculator_val
Version: 1.0
Summary: A simple calculator
Author-email: Valerio S <rgsvale@gmail.com>
Classifier: License :: OSI Approved :: MIT License
